{
    "Ar36": {
        "error": 3.300168111919143, 
        "error_type": "SEM", 
        "filter_outliers_dict": {
            "filter_outliers": true, 
            "iterations": 1, 
            "std_devs": 2
        }, 
        "fit": "linear", 
        "value": 571.9041177964426
    }, 
    "Ar37": {
        "error": 3.875601118569223e-07, 
        "error_type": "SEM", 
        "filter_outliers_dict": {
            "filter_outliers": true, 
            "iterations": 1, 
            "std_devs": 2
        }, 
        "fit": "linear", 
        "value": 2.0527878763560343e-06
    }, 
    "Ar38": {
        "error": 3.5290250720452397e-07, 
        "error_type": "SEM", 
        "filter_outliers_dict": {
            "filter_outliers": true, 
            "iterations": 1, 
            "std_devs": 2
        }, 
        "fit": "linear", 
        "value": 3.2954837133824156e-06
    }, 
    "Ar39": {
        "error": 3.8455139419910067e-07, 
        "error_type": "SEM", 
        "filter_outliers_dict": {
            "filter_outliers": true, 
            "iterations": 1, 
            "std_devs": 2
        }, 
        "fit": "linear", 
        "value": 1.4158882612015595e-06
    }, 
    "Ar40": {
        "error": 2.42666051503759e-06, 
        "error_type": "SEM", 
        "filter_outliers_dict": {
            "filter_outliers": true, 
            "iterations": 1, 
            "std_devs": 2
        }, 
        "fit": "linear", 
        "value": 0.0027669821217448307
    }
}