{
    "Ar36": {
        "error": 10.68858851568669, 
        "error_type": "SEM", 
        "filter_outliers_dict": {
            "filter_outliers": true, 
            "iterations": 1, 
            "std_devs": 2
        }, 
        "fit": "linear", 
        "value": 31.094251039048782
    }, 
    "Ar37": {
        "error": 8.494920942292934e-06, 
        "error_type": "SEM", 
        "filter_outliers_dict": {
            "filter_outliers": true, 
            "iterations": 1, 
            "std_devs": 2
        }, 
        "fit": "linear", 
        "value": 1.52899223479448e-06
    }, 
    "Ar38": {
        "error": 8.718027966815545e-06, 
        "error_type": "SEM", 
        "filter_outliers_dict": {
            "filter_outliers": true, 
            "iterations": 1, 
            "std_devs": 2
        }, 
        "fit": "linear", 
        "value": -1.4129717665944265e-05
    }, 
    "Ar39": {
        "error": 7.821061870534763e-06, 
        "error_type": "SEM", 
        "filter_outliers_dict": {
            "filter_outliers": true, 
            "iterations": 1, 
            "std_devs": 2
        }, 
        "fit": "linear", 
        "value": 2.2678376039292005e-06
    }, 
    "Ar40": {
        "error": 7.690784509725648e-06, 
        "error_type": "SEM", 
        "filter_outliers_dict": {
            "filter_outliers": true, 
            "iterations": 1, 
            "std_devs": 2
        }, 
        "fit": "linear", 
        "value": 0.000199374036752429
    }
}