{
    "AX": {
        "error": 1.3739354496262011e-06, 
        "error_type": "SEM", 
        "filter_outliers_dict": {
            "filter_outliers": true, 
            "iterations": 1, 
            "std_devs": 2
        }, 
        "fit": "average", 
        "value": 2.355345892018181e-06
    }, 
    "H1": {
        "error": 8.193605569737805e-07, 
        "error_type": "SEM", 
        "filter_outliers_dict": {
            "filter_outliers": true, 
            "iterations": 1, 
            "std_devs": 2
        }, 
        "fit": "average", 
        "value": 1.3659600655250003e-06
    }, 
    "H2": {
        "error": 7.979200688429621e-07, 
        "error_type": "SEM", 
        "filter_outliers_dict": {
            "filter_outliers": true, 
            "iterations": 1, 
            "std_devs": 2
        }, 
        "fit": "average", 
        "value": 1.716005113168421e-06
    }, 
    "L1": {
        "error": 9.2597696031054e-07, 
        "error_type": "SEM", 
        "filter_outliers_dict": {
            "filter_outliers": true, 
            "iterations": 1, 
            "std_devs": 2
        }, 
        "fit": "average", 
        "value": -1.0606420953448275e-06
    }, 
    "L2": {
        "error": 0.0, 
        "error_type": "SEM", 
        "filter_outliers_dict": {
            "filter_outliers": true, 
            "iterations": 1, 
            "std_devs": 2
        }, 
        "fit": "average", 
        "value": 0.0
    }
}